LICENSE.txt
README.rst
setup.py
gisrastertools/__init__.py
gisrastertools/gisrastertools.py
gisrastertools.egg-info/PKG-INFO
gisrastertools.egg-info/SOURCES.txt
gisrastertools.egg-info/dependency_links.txt
gisrastertools.egg-info/not-zip-safe
gisrastertools.egg-info/requires.txt
gisrastertools.egg-info/top_level.txt