Metadata-Version: 1.1
Name: gisrastertools
Version: 0.1
Summary: Tools for working with Geographical Information System Rasters
Home-page: http://github.com/ozak/gis-raster-tools
Author: Ömer Özak
Author-email: omer@omerozak.com
License: GPLv3
Platform: UNKNOWN
Classifier: Development Status :: 1 - Planning
Classifier: Topic :: Utilities
Classifier: License :: OSI Approved :: GNU General Public License v3 or later (GPLv3+)
Classifier: Intended Audience :: Developers
Classifier: Intended Audience :: Science/Research
Classifier: Operating System :: OS Independent
Classifier: Programming Language :: Python
Classifier: Topic :: Scientific/Engineering :: GIS
